etude_structure_package/__init__.py
etude_structure_package/sous_pk1/__init__.py
etude_structure_package/sous_pk1/m_1_1.py
etude_structure_package/sous_pk1/m_1_2.py
etude_structure_package/sous_pk2/__init__.py
etude_structure_package/sous_pk2/m_2_1.py
etude_structure_package-1.6.dist-info/METADATA
etude_structure_package-1.6.dist-info/WHEEL
etude_structure_package-1.6.dist-info/top_level.txt
etude_structure_package-1.6.dist-info/RECORD
